qls.py
engine/__init__.py
engine/compliance.py
engine/engine.py
engine/recommend.py
engine/remediator.py
engine/report_renderer.py
engine/reporter.py
engine/modules/__init__.py
engine/modules/aes.py
engine/modules/hybrid_tls.py
engine/modules/jwt.py
engine/modules/secrets.py
engine/modules/tls.py
qls_pro-0.3.5.dist-info/licenses/LICENSE.txt
qls_pro-0.3.5.dist-info/METADATA
qls_pro-0.3.5.dist-info/WHEEL
qls_pro-0.3.5.dist-info/entry_points.txt
qls_pro-0.3.5.dist-info/top_level.txt
qls_pro-0.3.5.dist-info/RECORD
