Metadata-Version: 2.4
Name: qls-pro
Version: 0.3.5
Summary: Quantum Liability Scanner – secrets, crypto misuse, and post-quantum risk in one command.
Author: Lucas Twitchell
Author-email: lucastwi11@gmail.com
License: Proprietary
Classifier: Programming Language :: Python :: 3
Classifier: Environment :: Console
Classifier: Intended Audience :: Developers
Classifier: Topic :: Security
Classifier: License :: Other/Proprietary License
Requires-Python: >=3.9
License-File: LICENSE.txt
Requires-Dist: cryptography>=42.0
Requires-Dist: rich>=13.7
Requires-Dist: markdown>=3.5
Requires-Dist: weasyprint>=65; platform_system != "Windows"
Requires-Dist: boto3>=1.34.0
Dynamic: license-file
